{
  "updated_at": "2025年10月19日 10:45",
  "zh": [
    {
      "title": "暧昧但不确立关系，年轻女孩们困在situationship里",
      "summary": "国内年轻女性正积极拥抱源自海外的\"情境关系\"（situationship），这种介于炮友与恋人间的模糊关系虽能提供情感陪伴与性亲密，却因缺乏承诺常导致情感内耗，折射出当代都市青年对婚姻压力的回避与亲密关系形态的新探索。",
      "link": "https://36kr.com/p/3512964102970499?f=rss"
    },
    {
      "title": "卖价过万的「大头娃娃」，成了「痛系」年轻人的新型奢侈品",
      "summary": "00后创业者李明威创立的偶域KIGLAND以998元低价颠覆Kigurumi头壳市场，通过标准化生产和AI建模技术将原本3000元起步的二次元玩偶服头壳价格拉至千元内，推动小众文化破圈，已获得奇绩创坛种子轮融资。",
      "link": "https://36kr.com/p/3512963909246089?f=rss"
    },
    {
      "title": "一位北京女CEO要敲钟了！",
      "summary": "轻松健康集团IPO获证监会备案，创始人杨胤从投资人转型CEO，将大病众筹平台轻松筹转型为数字健康服务平台，如今拥有1.7亿用户，去年营收9.45亿元。",
      "link": "https://36kr.com/p/3514451621075848?f=rss"
    },
    {
      "title": "英伟达与台积电合作，首片美国本土制造Blackwell芯片晶圆亮相",
      "summary": "英伟达CEO黄仁勋与台积电在美国亚利桑那州工厂共同揭幕首片Blackwell AI芯片晶圆，标志着英伟达斥资5000亿美元推动的\"美国制造\"芯片战略迈出关键一步。",
      "link": "https://36kr.com/p/3514429338426503?f=rss"
    },
    {
      "title": "起猛了，看见小红书抢闲鱼的饭碗了",
      "summary": "小红书内测“快捷售卖”功能进军二手交易市场，凭借精准算法实现供需匹配，但面临信任体系与售后保障等核心挑战，能否突破闲鱼等成熟平台的护城河仍是未知数。",
      "link": "https://36kr.com/p/3514290006186883?f=rss"
    },
    {
      "title": "马斯克：特斯拉 FSD V14.2 会大规模推送",
      "summary": "马斯克确认特斯拉将通过FSD V14.2版本全面推送全自动驾驶系统，新增\"疯狂麦克斯\"模式可应对拥堵路况，测试者反馈当前版本已解决95%的驾驶犹豫问题。",
      "link": "https://www.ithome.com/0/890/573.htm"
    },
    {
      "title": "华为商城上架鸿蒙智行享界 S9 汽车 1:18 合金车模：方向盘可联动车轮转向、后视镜可折叠，898 元",
      "summary": "华为商城推出鸿蒙智行享界S9合金车模，售价898元，支持四门两盖全开合及方向盘联动转向，提供寰宇红与浩宇蓝两种配色。",
      "link": "https://www.ithome.com/0/890/572.htm"
    },
    {
      "title": "realme 真我 GT8 Pro 搭载全腔对称式双 1115E 大师级扬声器，号称低音音质表现最好的手机之一",
      "summary": "真我GT8 Pro旗舰新机搭载双1115E全腔扬声器与N'Bass声学材料强化低音，配备骁龙8至尊版处理器、2亿像素潜望长焦及7000mAh电池，支持三重IP防护与全球21个5G频段，将于10月21日发布。",
      "link": "https://www.ithome.com/0/890/571.htm"
    },
    {
      "title": "岚图汽车卢放：安全绝非可选项，而是贯穿产品定义、开发与制造全流程的唯一准则",
      "summary": "岚图汽车董事长卢放重申安全为唯一准则，强调产品全流程安全一票否决制，并指出汽车不应被快消思维带偏方向。",
      "link": "https://www.ithome.com/0/890/569.htm"
    },
    {
      "title": "索尼确认《地平线：零之曙光》电影明年开拍，计划 2027 年上映",
      "summary": "索尼确认《地平线：零之曙光》真人电影剧本已完成，计划2026年开拍、2027年上映，目前正积极物色导演人选。",
      "link": "https://www.ithome.com/0/890/568.htm"
    },
    {
      "title": "量子位「MEET2026智能未来大会」启动！年度榜单征集中",
      "summary": "量子位启动MEET2026智能未来大会并征集年度榜单，汇聚科技领袖分享前沿洞见。",
      "link": "https://www.qbitai.com/2025/10/343231.html"
    },
    {
      "title": "首创“AI+真人”双保障模式！刚刚，百度健康推出7×24小时「能聊、有料、会管」AI管家",
      "summary": "百度健康推出AI管家，首创“AI+真人”双保障模式，提供7×24小时服务，36万医生参与数据标注与校验，确保服务精准可靠。",
      "link": "https://www.qbitai.com/2025/10/343152.html"
    },
    {
      "title": "卡帕西：强化学习很糟糕，但其他所有方法都更糟",
      "summary": "AI专家卡帕西称强化学习虽不完美，却是当前最优选择，并预测通用人工智能仍需十年发展。",
      "link": "https://www.qbitai.com/2025/10/343094.html"
    },
    {
      "title": "61岁退休后，华为海思创始总裁成了复旦北大清华老师",
      "summary": "61岁华为海思创始总裁退休后转型，在复旦、北大、清华担任教授，从商界领袖变身为高校导师。",
      "link": "https://www.qbitai.com/2025/10/343078.html"
    },
    {
      "title": "杨振宁教授千古！中国AI计算机产业因他而不同",
      "summary": "杨振宁推动中国AI计算机产业变革，其科学精神与跨界贡献影响深远。",
      "link": "https://www.qbitai.com/2025/10/343062.html"
    }
  ],
  "en": [
    {
      "title": "TiVo won the court battles, but lost the TV war",
      "summary": "TiVo在2000年代将DVR技术推向主流，其品牌名称甚至成为\"录制电视节目\"的代名词，如同谷歌和施乐一样深刻影响了日常用语。",
      "link": "https://www.theverge.com/tech/802254/tivo-time-warp-patent-courtoom-battles-lost-tv-war"
    },
    {
      "title": "Motorola’s Razr Ultra and the Marshall Emberton II top this week’s best deals",
      "summary": "2025款摩托罗拉Razr Ultra折叠手机迎来历史最低价，16GB+512GB版本现售999.99美元，较原价直降300美元，已在亚马逊和百思买同步开售。",
      "link": "https://www.theverge.com/tech/801962/motorola-razr-ultra-2025-foldable-marshall-emberton-ii-speaker-deal-sale"
    },
    {
      "title": "8BitDo’s new collection celebrates the NES’s 40th anniversary",
      "summary": "8BitDo推出NES40系列纪念任天堂北美发售40周年，包含升级版无线手柄、复古键盘和音箱。",
      "link": "https://www.theverge.com/news/801832/8bitdo-nintendo-nes-ultimate-2-controller-retro-keyboard-bluetooth-cube-speaker"
    },
    {
      "title": "Pokémon Legends: Z-A makes a big, welcome change for shiny hunters",
      "summary": "《宝可梦传说 Z-A》刚发布即引发热议：闪光宝可梦不会消失，玩家离开后返回仍可见，这一机制变革令收藏爱好者振奋。",
      "link": "https://www.theverge.com/games/802089/pokemon-legends-z-a-shiny-hunting"
    },
    {
      "title": "Easy Delivery Co. is a cozy, Lynchian dream",
      "summary": "David Lynch's cult classic \"Eraserhead\" often serves as a rite of passage for horror fans, typically discovered through unconventional means like late-night basement screenings or passionate recommendations.",
      "link": "https://www.theverge.com/games/800733/easy-delivery-co-review-steam"
    },
    {
      "title": "Roberta Williams’ The Colonel’s Bequest was a different type of adventure game",
      "summary": "经典冒险游戏《上校的遗愿》开创性地弱化传统解谜玩法，通过侦探调查机制推动叙事，成为互动小说式游戏设计的先驱。",
      "link": "https://arstechnica.com/gaming/2025/10/roberta-williams-the-colonels-bequest-was-a-different-type-of-adventure-game/"
    },
    {
      "title": "With deadline looming, 4 of 9 universities reject Trump’s “compact” to remake higher ed",
      "summary": "特朗普重塑高等教育的\"契约\"在九所大学中已有四所拒绝，但他仍向剩余五校施压。",
      "link": "https://arstechnica.com/culture/2025/10/with-deadline-looming-4-of-9-universities-reject-trumps-compact-to-remake-higher-ed/"
    },
    {
      "title": "Vaginal condition treatment update: Men should get treated, too",
      "summary": "新研究揭示：男性伴侣需同步治疗细菌性阴道病，打破传统单方治疗模式，实现更有效防治。",
      "link": "https://arstechnica.com/health/2025/10/vaginal-condition-treatment-update-men-should-get-treated-too/"
    },
    {
      "title": "Ring cameras are about to get increasingly chummy with law enforcement",
      "summary": "亚马逊旗下Ring与执法技术公司合作，其技术曾被移民海关执法局使用，引发隐私监控担忧。",
      "link": "https://arstechnica.com/gadgets/2025/10/ring-cameras-are-about-to-get-increasingly-chummy-with-law-enforcement/"
    },
    {
      "title": "Dead Ends is a fun, macabre medical history for kids",
      "summary": "医学史作家与历史漫画家联手推出儿童读物，用趣味插画和生动故事揭秘人体奥秘，激发小读者对科学的兴趣。",
      "link": "https://arstechnica.com/science/2025/10/dead-ends-is-a-fun-macabre-medical-history-for-kids/"
    },
    {
      "title": "The Download: the rehabilitation of AI art, and the scary truth about antimicrobial resistance",
      "summary": "AI艺术正从\"垃圾内容\"转向高端市场，生成式AI工具Midjourney和Runway推动艺术创作进入新阶段。",
      "link": "https://www.technologyreview.com/2025/10/17/1125895/the-download-the-rehabilitation-of-ai-art-and-the-scary-truth-about-antimicrobial-resistance/"
    },
    {
      "title": "From slop to Sotheby’s? AI art enters a new phase",
      "summary": "Despite widespread skepticism about AI-generated art's value, some creators are finding meaningful artistic applications amid the flood of low-quality content.",
      "link": "https://www.technologyreview.com/2025/10/17/1125193/ai-art-artist-new-chapter/"
    },
    {
      "title": "This startup thinks slime mold can help us design better cities",
      "summary": "初创公司Mireta利用存活6亿年的黏菌无脑智能特性，为现代城市基础设施设计提供抗灾韧性新方案。",
      "link": "https://www.technologyreview.com/2025/10/17/1125223/slime-design-better-cities-mireta/"
    },
    {
      "title": "Take our quiz: How much do you know about antimicrobial resistance?",
      "summary": "世卫组织警告：抗生素失效危机加剧，常见血液、肠道及尿路感染面临无药可医风险。",
      "link": "https://www.technologyreview.com/2025/10/16/1125853/antimicrobial-resistance-quiz-antibiotics-infection/"
    },
    {
      "title": "Unlocking the potential of SAF with book and claim in air freight",
      "summary": "航空业推出“预订与索赔”机制，允许企业通过资金支持可持续航空燃料（SAF）使用，助力实现减排目标，即使当地无法直接获取该燃料。",
      "link": "https://www.technologyreview.com/2025/10/16/1123850/unlocking-the-potential-of-saf-with-book-and-claim-in-air-freight/"
    },
    {
      "title": "Spyware maker NSO Group blocked from WhatsApp",
      "summary": "美法院永久禁止NSO集团入侵WhatsApp用户，但大幅削减其需向Meta支付的罚款金额。",
      "link": "https://techcrunch.com/2025/10/18/spyware-maker-nso-group-blocked-from-whatsapp/"
    },
    {
      "title": "Wikipedia says traffic is falling due to AI search summaries and social video",
      "summary": "维基百科流量受AI搜索摘要和短视频冲击下滑，传统知识平台面临数字时代挑战。",
      "link": "https://techcrunch.com/2025/10/18/wikipedia-says-traffic-is-falling-due-to-ai-search-summaries-and-social-video/"
    },
    {
      "title": "This top VC has bet close to 20% of his fund on teenagers — here’s why",
      "summary": "Eventbrite联合创始人Kevin Hartz意外发现青少年创业者潜力，将其作为新投资方向。",
      "link": "https://techcrunch.com/2025/10/18/this-top-vc-bet-close-to-20-of-his-fund-on-teenagers-heres-why/"
    },
    {
      "title": "YouTubers aren’t relying on ad revenue anymore — here’s how some are diversifying",
      "summary": "知名YouTuber纷纷拓展副业，部分创作者商业版图扩张速度已超越频道本身，展现内容创作者转型新趋势。",
      "link": "https://techcrunch.com/2025/10/18/youtubers-arent-relying-on-ad-revenue-anymore-heres-how-some-are-diversifying/"
    },
    {
      "title": "Too burned out to travel? This new app fakes your summer vacation photos for you",
      "summary": "AI app \"Endless Summer\" generates personalized fake vacation photos, letting users star in realistic travel scenes without leaving home.",
      "link": "https://techcrunch.com/2025/10/18/too-burned-out-to-travel-this-new-app-fakes-your-summer-vacation-photos-for-you/"
    }
  ]
}